odoo/addons/product_supplierinfo_for_customer_sale_quick/README.rst
odoo/addons/product_supplierinfo_for_customer_sale_quick/__init__.py
odoo/addons/product_supplierinfo_for_customer_sale_quick/__manifest__.py
odoo/addons/product_supplierinfo_for_customer_sale_quick/i18n/it.po
odoo/addons/product_supplierinfo_for_customer_sale_quick/i18n/product_supplierinfo_for_customer_sale_quick.pot
odoo/addons/product_supplierinfo_for_customer_sale_quick/models/__init__.py
odoo/addons/product_supplierinfo_for_customer_sale_quick/models/product_product.py
odoo/addons/product_supplierinfo_for_customer_sale_quick/models/sale_order.py
odoo/addons/product_supplierinfo_for_customer_sale_quick/readme/CONTRIBUTORS.rst
odoo/addons/product_supplierinfo_for_customer_sale_quick/readme/DESCRIPTION.rst
odoo/addons/product_supplierinfo_for_customer_sale_quick/static/description/icon.png
odoo/addons/product_supplierinfo_for_customer_sale_quick/static/description/index.html
odoo/addons/product_supplierinfo_for_customer_sale_quick/tests/__init__.py
odoo/addons/product_supplierinfo_for_customer_sale_quick/tests/test_product_supplierinfo_for_customer_sale_quick.py
odoo/addons/product_supplierinfo_for_customer_sale_quick/views/product_view.xml
odoo14_addon_product_supplierinfo_for_customer_sale_quick-14.0.1.0.1.dev3.dist-info/METADATA
odoo14_addon_product_supplierinfo_for_customer_sale_quick-14.0.1.0.1.dev3.dist-info/WHEEL
odoo14_addon_product_supplierinfo_for_customer_sale_quick-14.0.1.0.1.dev3.dist-info/top_level.txt
odoo14_addon_product_supplierinfo_for_customer_sale_quick-14.0.1.0.1.dev3.dist-info/RECORD
