Metadata-Version: 2.1
Name: odoo14-addon-product_supplierinfo_for_customer_sale_quick
Version: 14.0.1.0.1.dev3
Summary: Adapts the new fields added by Product Supplierinfo for Customer Salewith the Sale Quick module.
Home-page: https://github.com/OCA/sale-workflow
Author: Eduard Brahas, Ooops404, Odoo Community Association (OCA)
Author-email: support@odoo-community.org
License: AGPL-3
Classifier: Programming Language :: Python
Classifier: Framework :: Odoo
Classifier: Framework :: Odoo :: 14.0
Classifier: License :: OSI Approved :: GNU Affero General Public License v3
Requires-Python: >=3.6
Requires-Dist: odoo14-addon-product-supplierinfo-for-customer-sale
Requires-Dist: odoo14-addon-sale-quick
Requires-Dist: odoo<14.1dev,>=14.0a
